Workbook

Sheet Transactions
A1: 🟢 TALLY FORM FIELDS (Auto-populated from form) | M1: ⚙️ AUTO-GENERATED | Q1: 🔴 REVIEW (Manager/Accounts fills) | W1: 🤖 AUTO-FLAG (Helper)
A2: Date | B2: Amount | C2: Payment Type | D2: For | E2: Particular | F2: Platform | G2: Project | H2: Notes | I2: Source | J2: Transaction Done by | K2: Asked by | L2: Invoice File | M2: ID | N2: Submitted At | O2: Month | P2: Quarter | Q2: Status | R2: Wastage Flag | S2: Wastage Reason | T2: Approved By | U2: Review Date | V2: Reviewer Notes | W2: ⚠️ Auto-Flag | X2: Flag Reason
A3: 2025-01-15 | B3: 152000 | C3: Bank Transfer | D3: Outsource/PR | E3: Yahoo Finance PR Package - Monthly | F3: Accesswire | G3: Client PR Campaign | I3: Company | J3: Tarun | K3: Ankush | L3: https://drive.google.com/file/inv001 | M3: TXN001 | N3: 2025-01-15 10:30 | O3: Jan | P3: Q1 | Q3: Approved | R3: OK | T3: Ankush | U3: 2025-01-16 | W3: OK
A4: 2025-01-14 | B4: 85000 | C4: Credit Card | D4: Travel | E4: Dubai Flight + Hotel for Web3 Summit | F4: MakeMyTrip | G4: Web3 Summit Dubai | H4: 2 nights stay | I4: Company | J4: Ankush | K4: Ankush | L4: https://drive.google.com/file/inv002 | M4: TXN002 | N4: 2025-01-14 09:15 | O4: Jan | P4: Q1 | Q4: Approved | R4: OK | T4: Ankush | U4: 2025-01-14 | W4: ⚠️ HIGH VALUE | X4: Amount > ₹50K
A5: 2025-01-13 | B5: 45000 | C5: UPI | D5: Ads & Marketing | E5: Google Ads January Campaign | F5: Google Ads | G5: Lead Gen Q1 | I5: Company | J5: Tarun | K5: Ahmad | L5: https://drive.google.com/file/inv003 | M5: TXN003 | N5: 2025-01-13 14:20 | O5: Jan | P5: Q1 | Q5: Approved | R5: OK | T5: Tarun | U5: 2025-01-14 | W5: OK
A6: 2025-01-12 | B6: 1147500 | C6: Bank Transfer | D6: G Suite | E6: G Suite Annual Subscription - 850 IDs | F6: Google Workspace | G6: Email Infrastructure | H6: 350 IDs currently unused | I6: Company | J6: Megha | K6: Tarun | L6: https://drive.google.com/file/inv004 | M6: TXN004 | N6: 2025-01-12 11:00 | O6: Jan | P6: Q1 | Q6: Approved | R6: Wastage | S6: 350 unused accounts @ ₹1350/yr = ₹4.72L waste | T6: Ankush | U6: 2025-01-13 | V6: Need G Suite audit | W6: 🚨 VERY HIGH | X6: Amount > ₹1L
A7: 2025-01-11 | B7: 45000 | C7: Crypto | D7: Telegram | E7: Telegram Accounts Bulk Purchase - 1000 accounts | F7: TG Reseller | G7: Outreach Campaign | H7: For cold outreach | I7: Company | J7: Mayur | K7: Tarun | M7: TXN005 | N7: 2025-01-11 16:45 | O7: Jan | P7: Q1 | Q7: Pending | W7: ⚠️ NO INVOICE | X7: Invoice file missing
A8: 2025-01-10 | B8: 25000 | C8: Credit Card | D8: Tools & Subscriptions | E8: OpenAI API Credits | F8: OpenAI | G8: AI Automation | H8: Team usage | I8: Company | J8: Ashutosh | K8: Tarun | L8: https://drive.google.com/file/inv006 | M8: TXN006 | N8: 2025-01-10 10:00 | O8: Jan | P8: Q1 | Q8: Approved | R8: OK | T8: Tarun | U8: 2025-01-11 | W8: OK
A9: 2025-01-09 | B9: 12750 | C9: Crypto | D9: Telegram | E9: Telegram Account Purchase | F9: Buy Telegram account | G9: Outreach | H9: Suspicious seller | I9: Personal | J9: Vineet | K9: Rahul | M9: TXN007 | N9: 2025-01-09 15:30 | O9: Jan | P9: Q1 | Q9: Rejected | R9: Wastage | S9: Blacklisted vendor - fraud suspected | T9: Ankush | U9: 2025-01-10 | V9: Do not use this vendor again | W9: 🚨 BLACKLIST | X9: Vendor in blacklist
A10: 2025-01-08 | B10: 15000 | C10: UPI | D10: Tools & Subscriptions | E10: ReachInbox Annual Subscription | F10: ReachInbox | G10: Email Infrastructure | I10: Company | J10: Megha | K10: Tarun | L10: https://drive.google.com/file/inv008 | M10: TXN008 | N10: 2025-01-08 09:00 | O10: Jan | P10: Q1 | Q10: Approved | R10: OK | T10: Tarun | U10: 2025-01-09 | W10: OK
A11: 2025-01-07 | B11: 18000 | C11: Bank Transfer | D11: Content | E11: Content Writer Payment - 10 articles | F11: Freelancer | G11: Blog Content | I11: Company | J11: Abhijit | K11: Jai | L11: https://drive.google.com/file/inv009 | M11: TXN009 | N11: 2025-01-07 12:00 | O11: Jan | P11: Q1 | Q11: Approved | R11: OK | T11: Tarun | U11: 2025-01-08 | W11: OK
A12: 2025-01-06 | B12: 8500 | C12: Credit Card | D12: Tools & Subscriptions | E12: Midjourney Duplicate Subscription | F12: Midjourney | G12: Design Assets | H12: Already have one account | I12: Personal | J12: Jai | K12: Abhijit | M12: TXN010 | N12: 2025-01-06 14:00 | O12: Jan | P12: Q1 | Q12: Pending | W12: ⚠️ KEYWORD | X12: Contains 'Duplicate'
A13: 2025-01-05 | B13: 200000 | C13: Bank Transfer | D13: Ads & Marketing | E13: Blockchain Week Gold Sponsorship | F13: Blockchain Week | G13: Token2049 Event | H13: Booth + Branding | I13: Company | J13: Ahmad | K13: Ankush | L13: https://drive.google.com/file/inv011 | M13: TXN011 | N13: 2025-01-05 10:30 | O13: Jan | P13: Q1 | Q13: Approved | R13: OK | T13: Ankush | U13: 2025-01-05 | W13: 🚨 VERY HIGH | X13: Amount > ₹1L
A14: 2025-01-04 | B14: 5500 | C14: UPI | D14: Office | E14: Office Supplies - Stationery | F14: Amazon | G14: Office | I14: Company | J14: Kangana | K14: Ashwini | L14: https://drive.google.com/file/inv012 | M14: TXN012 | N14: 2025-01-04 11:00 | O14: Jan | P14: Q1 | Q14: Approved | R14: OK | T14: Ashwini | U14: 2025-01-04 | W14: OK

Sheet Dropdowns
A1: Payment Type | B1: For (Category) | C1: Source | D1: Team Members | E1: Status (Review) | F1: Wastage Flag (Review) | G1: Approvers
A2: UPI | B2: Outsource/PR | C2: Company | D2: Ankush | E2: Pending | F2: OK | G2: Ankush
A3: Bank Transfer | B3: Travel | C3: Personal | D3: Ahmad | E3: Approved | F3: Review | G3: Tarun
A4: Credit Card | B4: Ads & Marketing | C4: Reimbursement | D4: Tarun | E4: Rejected | F4: Wastage | G4: Ashwini
A5: Cash | B5: Tools & Subscriptions | D5: Megha | E5: On Hold | G5: Ahmad
A6: PayPal | B6: Telegram | D6: Rahul
A7: Crypto | B7: G Suite | D7: Vineet
A8: Cheque | B8: Content | D8: Mayur
B9: Office | D9: Ashutosh
B10: Miscellaneous | D10: Lakshya
D11: Roshan
D12: Jagruti
D13: Dhruv
D14: Abhijit
D15: Jai
D16: Pankaj
D17: Ashwini
D18: Kangana

Sheet Summary
A1: TBP MEDIA - EXPENSE SUMMARY
A2: Dashboard data source - auto-calculated
A4: TOTALS
A5: Total Expenses (All) | B5: =SUM(Transactions!B:B) -> 1759250
A6: Approved Expenses | B6: =SUMIF(Transactions!Q:Q,"Approved",Transactions!B:B) -> 1693000
A7: Pending Review | B7: =SUMIF(Transactions!Q:Q,"Pending",Transactions!B:B) -> 53500
A8: Rejected | B8: =SUMIF(Transactions!Q:Q,"Rejected",Transactions!B:B) -> 12750
A9: Transaction Count | B9: =COUNTA(Transactions!M:M)-1 -> 13
A11: WASTAGE (Confirmed by Reviewer)
A12: Confirmed Wastage (₹) | B12: =SUMIF(Transactions!R:R,"Wastage",Transactions!B:B) -> 1160250
A13: Wastage Count | B13: =COUNTIF(Transactions!R:R,"Wastage") -> 2
A14: Needs Review (₹) | B14: =SUMIF(Transactions!R:R,"Review",Transactions!B:B) -> 0
A16: AUTO-FLAGGED (Pending Review)
A17: Total Flagged | B17: =COUNTIF(Transactions!W:W,"<>OK")-1 -> 1048569
A18: High Value Flags | B18: =COUNTIF(Transactions!W:W,"*HIGH*") -> 3
A19: Missing Invoice Flags | B19: =COUNTIF(Transactions!W:W,"*INVOICE*") -> 1
A20: Blacklist Flags | B20: =COUNTIF(Transactions!W:W,"*BLACKLIST*") -> 1
A22: BY CATEGORY (For)
A23: Outsource/PR | B23: =SUMIF(Transactions!D:D,"Outsource/PR",Transactions!B:B) -> 152000
A24: Travel | B24: =SUMIF(Transactions!D:D,"Travel",Transactions!B:B) -> 85000
A25: Ads & Marketing | B25: =SUMIF(Transactions!D:D,"Ads & Marketing",Transactions!B:B) -> 245000
A26: Tools & Subscriptions | B26: =SUMIF(Transactions!D:D,"Tools & Subscriptions",Transactions!B:B) -> 48500
A27: Telegram | B27: =SUMIF(Transactions!D:D,"Telegram",Transactions!B:B) -> 57750
A28: G Suite | B28: =SUMIF(Transactions!D:D,"G Suite",Transactions!B:B) -> 1147500
A29: Content | B29: =SUMIF(Transactions!D:D,"Content",Transactions!B:B) -> 18000
A30: Office | B30: =SUMIF(Transactions!D:D,"Office",Transactions!B:B) -> 5500
A32: BY SOURCE
A33: Company | B33: =SUMIF(Transactions!I:I,"Company",Transactions!B:B) -> 1738000
A34: Personal | B34: =SUMIF(Transactions!I:I,"Personal",Transactions!B:B) -> 21250
A35: Reimbursement | B35: =SUMIF(Transactions!I:I,"Reimbursement",Transactions!B:B) -> 0
A37: MISSING INVOICES
A38: Count (Invoice empty) | B38: =COUNTBLANK(Transactions!L3:L1000)-COUNTBLANK(Transactions!A3:A1000) -> 3

Sheet Tally Mapping
A1: TALLY FORM → MASTER SHEET COLUMN MAPPING
A3: TALLY FIELD | B3: REQUIRED | C3: SHEET COLUMN
A4: Date | B4: ✓ | C4: A - Date
A5: Amount | B5: ✓ | C5: B - Amount
A6: Payment Type (dropdown) | B6: ✓ | C6: C - Payment Type
A7: For (dropdown) | B7: ✓ | C7: D - For (Category)
A8: Particular | B8: ✓ | C8: E - Particular (Description)
A9: Platform | B9: ✓ | C9: F - Platform (Vendor)
A10: Project | B10: ✓ | C10: G - Project
A11: Notes | C11: H - Notes
A12: Source (dropdown) | B12: ✓ | C12: I - Source
A13: Transaction Done by (dropdown) | B13: ✓ | C13: J - Transaction Done by
A14: Asked by (dropdown) | B14: ✓ | C14: K - Asked by
A15: File upload | C15: L - Invoice File (as link)
A16: Email | C16: (For notifications only)
A18: AUTO-FILLED COLUMNS (System generates):
C19: M - ID (auto-increment)
C20: N - Submitted At (timestamp)
C21: O - Month (from Date)
C22: P - Quarter (from Date)
C23: W - Auto-Flag (formula)
C24: X - Flag Reason (formula)
A26: REVIEW COLUMNS (Manager fills LATER):
C27: Q - Status (Pending/Approved/Rejected)
C28: R - Wastage Flag (OK/Review/Wastage)
C29: S - Wastage Reason
C30: T - Approved By
C31: U - Review Date
C32: V - Reviewer Notes

Sheet Auto-Detection Rules
A1: AUTO-FLAG RULES (Column W)
A2: These formulas SUGGEST potential issues - Reviewer makes final decision
A4: FLAG | B4: CONDITION
A5: 🚨 BLACKLIST | B5: Platform (F) matches blacklisted vendor
A6: 🚨 VERY HIGH | B6: Amount (B) > ₹1,00,000
A7: ⚠️ HIGH VALUE | B7: Amount (B) > ₹50,000
A8: ⚠️ NO INVOICE | B8: Invoice File (L) is empty
A9: ⚠️ KEYWORD | B9: Particular (E) contains: duplicate, unused, fraud, cancelled, refund
A10: ⚠️ PERSONAL HIGH | B10: Source = 'Personal' AND Amount > ₹25,000
A11: OK | B11: No issues detected
A13: BLACKLISTED VENDORS (add as identified):
A14: Buy Telegram account | B14: Fraud reported Jan 2025
A16: FORMULA EXAMPLE (for Column W):
A17: =IF(F3="Buy Telegram account","🚨 BLACKLIST",IF(B3>100000,"🚨 VERY HIGH",IF(B3>50000,"⚠️ HIGH VALUE",IF(L3="","⚠️ NO INVOICE",IF(OR(ISNUMBER(SEARCH("duplicate",E3)),ISNUMBER(SEARCH("unused",E3))),"⚠️ KEYWORD","OK"))))) -> ⚠️ NO INVOICE

Sheet Review Workflow
A1: EXPENSE REVIEW WORKFLOW
A3: STEP 1: SUBMISSION
A4: Team member fills Tally form → Data flows to Transactions sheet (A-L)
A5: System auto-generates: ID, Timestamp, Month, Quarter (M-P)
A6: System auto-flags potential issues (W-X)
A7: Status auto-set to 'Pending'
A9: STEP 2: MANAGER/ACCOUNTS REVIEW
A10: Filter: Status = 'Pending'
A11: Sort by: Auto-Flag column to see flagged items first
A12: For each expense, fill columns Q-V:
A13: Q - Status: Approve / Reject / On Hold
A14: R - Wastage Flag: OK / Review / Wastage
... A28: Founder sees reviewed, final numbers
